{
  "name": "Korea South",
  "iso3": "KOR",
  "states": [
    {
      "name": "Busan",
      "state_code": "26"
    },
    {
      "name": "Daegu",
      "state_code": "27"
    },
    {
      "name": "Daejeon",
      "state_code": "30"
    },
    {
      "name": "Gangwon Province",
      "state_code": "42"
    },
    {
      "name": "Gwangju",
      "state_code": "29"
    },
    {
      "name": "Gyeonggi Province",
      "state_code": "41"
    },
    {
      "name": "Incheon",
      "state_code": "28"
    },
    {
      "name": "Jeju",
      "state_code": "49"
    },
    {
      "name": "North Chungcheong Province",
      "state_code": "43"
    },
    {
      "name": "North Gyeongsang Province",
      "state_code": "47"
    },
    {
      "name": "North Jeolla Province",
      "state_code": "45"
    },
    {
      "name": "Sejong City",
      "state_code": "50"
    },
    {
      "name": "Seoul",
      "state_code": "11"
    },
    {
      "name": "South Chungcheong Province",
      "state_code": "44"
    },
    {
      "name": "South Gyeongsang Province",
      "state_code": "48"
    },
    {
      "name": "South Jeolla Province",
      "state_code": "46"
    },
    {
      "name": "Ulsan",
      "state_code": "31"
    }
  ]
}